course_access_groups/__init__.py
course_access_groups/acl_backends.py
course_access_groups/admin.py
course_access_groups/apps.py
course_access_groups/feature_flag.py
course_access_groups/filters.py
course_access_groups/models.py
course_access_groups/openedx_modules.py
course_access_groups/permissions.py
course_access_groups/serializers.py
course_access_groups/signals.py
course_access_groups/urls.py
course_access_groups/validators.py
course_access_groups/views.py
course_access_groups/migrations/0001_initial.py
course_access_groups/migrations/0002_fix_group_course_typo_plural.py
course_access_groups/migrations/0002_fix_public_course_typo.py
course_access_groups/migrations/__init__.py
course_access_groups-0.6.1.dist-info/LICENSE.txt
course_access_groups-0.6.1.dist-info/METADATA
course_access_groups-0.6.1.dist-info/WHEEL
course_access_groups-0.6.1.dist-info/entry_points.txt
course_access_groups-0.6.1.dist-info/top_level.txt
course_access_groups-0.6.1.dist-info/RECORD
