Metadata-Version: 2.1
Name: course-access-groups
Version: 0.6.1
Summary: An Open edX plugin to customize courses access by grouping learners and assigning different permissions to groups.
Home-page: https://github.com/appsembler/course-access-groups
Author: Appsembler
Author-email: omar@appsembler.com
Keywords: Django Appsembler
Classifier: Development Status :: 3 - Alpha
Classifier: Framework :: Django
Classifier: Framework :: Django :: 2.0
Classifier: Intended Audience :: Developers
Classifier: License :: OSI Approved :: MIT License
Classifier: Natural Language :: English
Classifier: Programming Language :: Python :: 3
Classifier: Programming Language :: Python :: 3.6
License-File: LICENSE.txt
Requires-Dist: XBlock
Requires-Dist: Django
Requires-Dist: django-model-utils
Requires-Dist: tahoe-sites
Requires-Dist: edx-organizations
Requires-Dist: edx-opaque-keys
Requires-Dist: django-filter
